fandango/CHANGELOG
fandango/VERSION
fandango/__init__.py
fandango/arrays.py
fandango/callbacks.py
fandango/db.py
fandango/debug.py
fandango/devslist.py
fandango/dicts.py
fandango/doc.py
fandango/dynamic.py
fandango/excepts.py
fandango/functional.py
fandango/linos.py
fandango/log.py
fandango/objects.py
fandango/pipes.py
fandango/qt.py
fandango/servers.py
fandango/threads.py
fandango/web.py
fandango/device/DDebug.py
fandango/device/Dev4Tango.py
fandango/device/DynamicDS.py
fandango/device/FolderDS.py
fandango/device/FolderGUI.py
fandango/device/WorkerDS.py
fandango/device/__init__.py
fandango/interface/CopyCatDS.py
fandango/interface/__init__.py
fandango/interface/inheritance.py
fandango/scripts/__init__.py
fandango/scripts/servers_lite.py
fandango/scripts/setup.ds.py
fandango/scripts/tango_create_device.py
fandango/scripts/tango_create_starter.py
fandango/tango/__init__.py
fandango/tango/command.py
fandango/tango/defaults.py
fandango/tango/dynattr.py
fandango/tango/export.py
fandango/tango/methods.py
fandango/tango/search.py
fandango/tango/tangoeval.py
fandango/testing/__init__.py
fandango/testing/check_callbacks.py
fandango/testing/check_fandango.py
fandango/testing/checkmodule.py
fandango/testing/gen_test_file.py
fandango/testing/simulation.py
fandango/widget/__init__.py
fandango-15.1.2.data/scripts/CopyCatDS
fandango-15.1.2.data/scripts/DynamicDS
fandango-15.1.2.data/scripts/FolderDS
fandango-15.1.2.data/scripts/WorkerDS
fandango-15.1.2.data/scripts/csv2tango
fandango-15.1.2.data/scripts/ctds
fandango-15.1.2.data/scripts/fandango
fandango-15.1.2.data/scripts/folder-gui
fandango-15.1.2.data/scripts/sardanact
fandango-15.1.2.data/scripts/tango2csv
fandango-15.1.2.data/scripts/tango2json
fandango-15.1.2.data/scripts/tango_cleanup
fandango-15.1.2.data/scripts/tango_host
fandango-15.1.2.data/scripts/tango_monitor
fandango-15.1.2.data/scripts/tango_property
fandango-15.1.2.data/scripts/tango_servers
tests/__init__.py
tests/definitions.py
tests/test_functional.py
fandango-15.1.2.dist-info/AUTHORS
fandango-15.1.2.dist-info/LICENSE
fandango-15.1.2.dist-info/METADATA
fandango-15.1.2.dist-info/WHEEL
fandango-15.1.2.dist-info/top_level.txt
fandango-15.1.2.dist-info/RECORD
