Metadata-Version: 2.1
Name: fandango
Version: 15.1.2
Summary: Simplify the configuration of big Tango control systems
Author: Sergi Rubio
Author-email: srubio@cells.es
Platform: Linux,Windows XP/Vista/7/8
Classifier: Development Status :: 5 - Production/Stable
Classifier: Environment :: Other Environment
Classifier: Intended Audience :: Developers
Classifier: License :: OSI Approved :: GNU Lesser General Public License v3 or later (LGPLv3+)
Classifier: Natural Language :: English
Classifier: Operating System :: Microsoft :: Windows
Classifier: Operating System :: POSIX
Classifier: Operating System :: POSIX :: Linux
Classifier: Operating System :: Unix
Classifier: Programming Language :: Python
Classifier: Topic :: Scientific/Engineering
Classifier: Topic :: Software Development :: Libraries
Requires-Python: >3.6
License-File: LICENSE
License-File: AUTHORS
Requires-Dist: future
Provides-Extra: tests
Requires-Dist: pytest ; extra == 'tests'
Requires-Dist: pytest-freezegun ; extra == 'tests'
Requires-Dist: pytz ; extra == 'tests'
Requires-Dist: freezegun ; extra == 'tests'
Requires-Dist: future ; extra == 'tests'
